django_twined/__init__.py
django_twined/apps.py
django_twined/exceptions.py
django_twined/fields.py
django_twined/urls.py
django_twined/views.py
django_twined/admin/__init__.py
django_twined/admin/admin.py
django_twined/admin/fieldsets.py
django_twined/admin/mixins.py
django_twined/admin/proxy.py
django_twined/management/__init__.py
django_twined/management/commands/__init__.py
django_twined/management/commands/sync_data_stores.py
django_twined/migrations/0001_initial.py
django_twined/migrations/0002_slug_unique_and_not_editable.py
django_twined/migrations/0003_rename_slug_to_name.py
django_twined/migrations/0004_add_timestamps.py
django_twined/migrations/0005_question_date_help_text.py
django_twined/migrations/0006_service_revisions_and_events.py
django_twined/migrations/0007_registered_to_revision.py
django_twined/migrations/0008_registered_relations_to_nullable.py
django_twined/migrations/0009_remove_registered_services.py
django_twined/migrations/0010_alter_servicerevision_project_name.py
django_twined/migrations/0011_remove_servicerevision_topic_id.py
django_twined/migrations/0012_servicerevision_is_default.py
django_twined/migrations/0013_alter_serviceusageevent_question.py
django_twined/migrations/0014_question_status.py
django_twined/migrations/__init__.py
django_twined/models/__init__.py
django_twined/models/datastores.py
django_twined/models/questions.py
django_twined/models/service_revisions.py
django_twined/models/service_usage_events.py
django_twined/models/querysets/__init__.py
django_twined/models/querysets/datastore_queryset.py
django_twined/signals/__init__.py
django_twined/signals/receivers.py
django_twined/signals/senders.py
django_twined/templates/admin/question_ask_row.html
django_twined/templates/django_twined/question_changeform.html
django_twined/templatetags/__init__.py
django_twined/templatetags/question_ask_row.py
django_twined-0.8.17.dist-info/licenses/LICENSE
django_twined-0.8.17.dist-info/METADATA
django_twined-0.8.17.dist-info/WHEEL
django_twined-0.8.17.dist-info/top_level.txt
django_twined-0.8.17.dist-info/RECORD
