Metadata-Version: 2.4
Name: django-twined
Version: 0.8.17
Summary: A django app to manage octue services
Author-email: Tom Clark <tom@octue.com>, Marcus Lugg <marcus@octue.com>
License-Expression: MIT
Project-URL: Changelog, https://github.com/octue/django-twined/releases
Project-URL: Documentation, https://django-twined.readthedocs.io/
Project-URL: Homepage, https://github.com/octue/django-twined
Project-URL: Issues, https://github.com/octue/django-twined/issues
Project-URL: Repository, https://github.com/octue/django-twined
Keywords: django,services,octue,twined
Classifier: Development Status :: 4 - Beta
Classifier: Intended Audience :: Developers
Classifier: Topic :: Software Development :: Libraries :: Python Modules
Classifier: Framework :: Django
Classifier: Framework :: Django :: 3.2
Classifier: Framework :: Django :: 4.1
Classifier: Framework :: Django :: 4.2
Classifier: Framework :: Django :: 5.0
Classifier: Framework :: Django :: 5.1
Classifier: Framework :: Django :: 5.2
Classifier: Programming Language :: Python :: 3.10
Classifier: Programming Language :: Python :: 3.11
Classifier: Programming Language :: Python :: 3.12
Classifier: Programming Language :: Python :: 3.13
Classifier: Operating System :: OS Independent
Requires-Python: >=3.10
License-File: LICENSE
Requires-Dist: django<5.1,>=3.0
Requires-Dist: octue<0.64.0,>=0.52.0
Requires-Dist: django-gcp<1,>=0.11.5
Requires-Dist: django-jsoneditor<0.3,>=0.2.2
Requires-Dist: django-model-utils<6,>4.2.0
Dynamic: license-file
